silvera/__init__.py
silvera/const.py
silvera/core.py
silvera/exceptions.py
silvera/resolvers.py
silvera/run.py
silvera/utils.py
silvera/cli/__init__.py
silvera/evaluation/__init__.py
silvera/evaluation/builtin.py
silvera/evaluation/registration.py
silvera/export/__init__.py
silvera/generator/__init__.py
silvera/generator/generator.py
silvera/generator/java_generator.py
silvera/generator/platforms.py
silvera/generator/project_struct.py
silvera/generator/registration.py
silvera/generator/templates/java/Dockerfile.template
silvera/generator/templates/java/docker_compose.template
silvera/generator/templates/java/run_cmd.template
silvera/generator/templates/java/run_sh.template
silvera/generator/templates/java/api-gateway/application_properties.template
silvera/generator/templates/java/api-gateway/main.template
silvera/generator/templates/java/api-gateway/pom_xml.template
silvera/generator/templates/java/config-server/application_properties.template
silvera/generator/templates/java/config-server/main.template
silvera/generator/templates/java/config-server/pom_xml.template
silvera/generator/templates/java/eureka/Dockerfile.template
silvera/generator/templates/java/eureka/eureka_application.template
silvera/generator/templates/java/eureka/eureka_main.template
silvera/generator/templates/java/eureka/eureka_pom_xml.template
silvera/generator/templates/java/service/messaging/application_properties.template
silvera/generator/templates/java/service/messaging/main.template
silvera/generator/templates/java/service/messaging/pom_xml.template
silvera/generator/templates/java/service/messaging/config/deserializer.template
silvera/generator/templates/java/service/messaging/config/kafka_config.template
silvera/generator/templates/java/service/messaging/controller/controller.template
silvera/generator/templates/java/service/messaging/domain/class.template
silvera/generator/templates/java/service/messaging/message/class.template
silvera-0.3.1.dist-info/LICENSE
silvera-0.3.1.dist-info/METADATA
silvera-0.3.1.dist-info/WHEEL
silvera-0.3.1.dist-info/entry_points.txt
silvera-0.3.1.dist-info/top_level.txt
silvera-0.3.1.dist-info/RECORD
