Metadata-Version: 2.1
Name: silvera
Version: 0.3.1
Summary: Tool for generating microservice architectures.
Home-page: https://github.com/alensuljkanovic/silvera
Author: Alen Suljkanovic
Author-email: alienized91@gmail.com
License: MIT
Keywords: microservices dsl generator compiler
Platform: UNKNOWN
Classifier: Development Status :: 5 - Production/Stable
Classifier: Intended Audience :: Developers
Classifier: Intended Audience :: Information Technology
Classifier: Intended Audience :: Science/Research
Classifier: Topic :: Software Development :: Interpreters
Classifier: Topic :: Software Development :: Compilers
Classifier: Topic :: Software Development :: Libraries :: Python Modules
Classifier: License :: OSI Approved :: MIT License
Classifier: Operating System :: OS Independent
Classifier: Programming Language :: Python
License-File: LICENSE
Requires-Dist: textx
Requires-Dist: jinja2
Requires-Dist: click
